maltiverse/__init__.py
maltiverse/maltiverse.py
maltiverse/test_maltiverse.py
maltiverse-1.2.0.dist-info/LICENSE
maltiverse-1.2.0.dist-info/METADATA
maltiverse-1.2.0.dist-info/WHEEL
maltiverse-1.2.0.dist-info/top_level.txt
maltiverse-1.2.0.dist-info/RECORD
