Metadata-Version: 2.1
Name: maltiverse
Version: 1.2.0
Summary: Wrapper for the Maltiverse API
Home-page: https://github.com/maltiverse/maltiverse-python
Download-URL: https://github.com/maltiverse/python-maltiverse/archive/master.zip
Author: Antonio Gomez
Author-email: Antonio Gomez <antonio.gomez@maltiverse.com>, Jorge Lopez <jorge.lopez@maltiverse.com>, Developers <dev@maltiverse.com>
License: MIT License
Project-URL: Homepage, https://github.com/maltiverse/python-maltiverse
Project-URL: Bug Tracker, https://github.com/maltiverse/python-maltiverse/issues
Keywords: maltiverse,API,threat intelligence,IoC,blacklist,search engine
Classifier: Development Status :: 5 - Production/Stable
Classifier: Intended Audience :: Developers
Classifier: Topic :: Software Development :: Build Tools
Classifier: License :: OSI Approved :: MIT License
Classifier: Programming Language :: Python :: 3
Classifier: Programming Language :: Python :: 3.7
Classifier: Programming Language :: Python :: 3.8
Classifier: Programming Language :: Python :: 3.9
Requires-Python: >=3.7
License-File: LICENSE
Requires-Dist: requests
Requires-Dist: PyJWT
